viavi/fiberparse/Data/Data.py
viavi/fiberparse/Data/MSORData.py
viavi/fiberparse/Data/SORData.py
viavi/fiberparse/Dataset/Dataset.py
viavi/fiberparse/Dataset/OTDRDataset.py
viavi/fiberparse/FileParser/FileParser.py
viavi/fiberparse/FileParser/MSORParser.py
viavi/fiberparse/FileParser/SORParser.py
viavi/fiberparse/Utils/HelpersXMLParsing.py
viavi/fiberparse/__init__.py
viavi_fiberparse-0.1.1.dist-info/LICENSE
viavi_fiberparse-0.1.1.dist-info/METADATA
viavi_fiberparse-0.1.1.dist-info/WHEEL
viavi_fiberparse-0.1.1.dist-info/RECORD
