Metadata-Version: 2.1
Name: viavi.fiberparse
Version: 0.1.1
Summary: Sor and other viavi file Python API
Author: Anthony GONIN
Author-email: anthony.gonin@viavisolutions.com
Requires-Python: >=3.9,<4.0
Classifier: Programming Language :: Python :: 3
Classifier: Programming Language :: Python :: 3.9
Classifier: Programming Language :: Python :: 3.10
Classifier: Programming Language :: Python :: 3.11
Classifier: Programming Language :: Python :: 3.12
Requires-Dist: dataclass-wizard (>=0.22.2,<0.23.0)
Requires-Dist: lxml (>=4.9.3,<5.0.0)
Requires-Dist: pydantic (>=1.10.14)
Requires-Dist: type-checker-decorators (>=0.1.3,<0.2.0)
